webdriverdownloader2/__init__.py
webdriverdownloader2/cli.py
webdriverdownloader2/util.py
webdriverdownloader2/webdriverdownloader2.py
webdriverdownloader2-2.0.3.dist-info/LICENSE
webdriverdownloader2-2.0.3.dist-info/METADATA
webdriverdownloader2-2.0.3.dist-info/WHEEL
webdriverdownloader2-2.0.3.dist-info/entry_points.txt
webdriverdownloader2-2.0.3.dist-info/top_level.txt
webdriverdownloader2-2.0.3.dist-info/RECORD
