Metadata-Version: 2.1
Name: webdriverdownloader2
Version: 2.0.3
Summary: Python module and CLI tool for facilitating download and deploy of WebDriver binaries.
Home-page: https://github.com/bodharma/webdriverdownloader2
Author-email: leonidessaguisagjr@gmail.com
Maintainer: Bohdan Lesiv
Maintainer-email: boghdanlesiv@gmail.com
License: MIT
Platform: UNKNOWN
Classifier: Development Status :: 5 - Production/Stable
Classifier: Environment :: Console
Classifier: Intended Audience :: Developers
Classifier: Intended Audience :: End Users/Desktop
Classifier: License :: OSI Approved :: MIT License
Classifier: Programming Language :: Python
Classifier: Programming Language :: Python :: 3
Classifier: Programming Language :: Python :: 3.7
Classifier: Programming Language :: Python :: 3.8
Classifier: Programming Language :: Python :: 3.9
Classifier: Topic :: Software Development :: Libraries
Classifier: Topic :: Software Development :: Quality Assurance
Classifier: Topic :: Software Development :: Testing
Classifier: Topic :: Utilities
Requires-Dist: beautifulsoup4
Requires-Dist: requests
Requires-Dist: tqdm
Requires-Dist: loguru
Requires-Dist: py-cpuinfo
